[
  {
    "layerID": 0,
    "z": 4095,
    "param": 0,
    "state": 0,
    "typeTrans": 0,
    "tileCount": 896,
    "fileName": "anfrst_2-4095-0-0-0-0.png"
  },
  {
    "layerID": 1,
    "z": 16,
    "param": 0,
    "state": 0,
    "typeTrans": 0,
    "tileCount": 102,
    "fileName": "anfrst_2-16-1-0-0-0.png"
  },
  {
    "layerID": 1,
    "z": 2176,
    "param": 0,
    "state": 0,
    "typeTrans": 0,
    "tileCount": 11,
    "fileName": "anfrst_2-2176-1-0-0-0.png"
  },
  {
    "layerID": 1,
    "z": 2208,
    "param": 0,
    "state": 0,
    "typeTrans": 0,
    "tileCount": 9,
    "fileName": "anfrst_2-2208-1-0-0-0.png"
  },
  {
    "layerID": 1,
    "z": 2217,
    "param": 0,
    "state": 0,
    "typeTrans": 0,
    "tileCount": 6,
    "fileName": "anfrst_2-2217-1-0-0-0.png"
  },
  {
    "layerID": 1,
    "z": 2232,
    "param": 0,
    "state": 0,
    "typeTrans": 0,
    "tileCount": 18,
    "fileName": "anfrst_2-2232-1-0-0-0.png"
  },
  {
    "layerID": 1,
    "z": 2240,
    "param": 0,
    "state": 0,
    "typeTrans": 0,
    "tileCount": 27,
    "fileName": "anfrst_2-2240-1-0-0-0.png"
  },
  {
    "layerID": 1,
    "z": 3840,
    "param": 0,
    "state": 0,
    "typeTrans": 0,
    "tileCount": 63,
    "fileName": "anfrst_2-3840-1-0-0-0.png"
  },
  {
    "layerID": 3,
    "z": 0,
    "param": 0,
    "state": 0,
    "typeTrans": 1,
    "tileCount": 127,
    "fileName": "anfrst_2-0-3-1-0-0.png"
  }
]